chatgpt_functions/__init__.py
chatgpt_functions/chatgpt.py
chatgpt_functions/chatgpt_function.py
chatgpt_functions/chatgpt_types.py
chatgpt_functions/function_parameters.py
chatgpt_functions-0.1.10.dist-info/LICENSE
chatgpt_functions-0.1.10.dist-info/METADATA
chatgpt_functions-0.1.10.dist-info/WHEEL
chatgpt_functions-0.1.10.dist-info/top_level.txt
chatgpt_functions-0.1.10.dist-info/RECORD
