Metadata-Version: 2.1
Name: chatgpt-functions
Version: 0.1.10
Summary: Wrapper over the gpt3.5 model, capable of calling functions
Home-page: https://github.com/Wellmare/chatgpt-functions
Author: Wellmare
Author-email: ivan.kolipov@gmail.com
Keywords: chatgpt functions gpt
Classifier: Programming Language :: Python :: 3.10
Classifier: License :: OSI Approved :: MIT License
Classifier: Operating System :: OS Independent
Requires-Python: >=3.7
License-File: LICENSE
Requires-Dist: loguru (==0.7.0)
Requires-Dist: openai (==0.27.8)
Requires-Dist: python-dotenv (==1.0.0)
